{
    "entityNumberCounter": 7,
    "entities": [
        {
            "hierarchyOrder": 2.0,
            "name": "Floor Base Concrete 01",
            "uniqueNumber": 3,
            "parent": -1,
            "exposed": true,
            "collapsedChildren": false,
            "components": [
                {
                    "name": "transform",
                    "specifics": "{\"pos\":{\"x\":8.0,\"y\":0.0,\"z\":8.0},\"rot\":{\"x\":0.0,\"y\":0.0,\"z\":0.0,\"w\":1.0},\"scale\":{\"x\":1.0,\"y\":1.0,\"z\":1.0}}"
                },
                {
                    "name": "GLTFShape",
                    "specifics": "{\"assetID\":\"014c1831-f31a-4fee-8df6-7fd5997b5a2b\"}"
                }
            ]
        },
        {
            "hierarchyOrder": 3.0,
            "name": "Plain Glass Wall",
            "uniqueNumber": 4,
            "parent": -1,
            "exposed": false,
            "collapsedChildren": false,
            "components": [
                {
                    "name": "transform",
                    "specifics": "{\"pos\":{\"x\":16.0,\"y\":0.14900000393390656,\"z\":0.29499998688697817},\"rot\":{\"x\":0.0,\"y\":0.0,\"z\":0.0,\"w\":1.0},\"scale\":{\"x\":7.584000110626221,\"y\":1.6950000524520875,\"z\":0.9929999709129334}}"
                },
                {
                    "name": "GLTFShape",
                    "specifics": "{\"assetID\":\"87e787f9-b794-46a3-bb8f-8a8b1fdcbc7d\"}"
                }
            ]
        },
        {
            "hierarchyOrder": 1.0,
            "name": "Plain Glass Wall",
            "uniqueNumber": 5,
            "parent": -1,
            "exposed": false,
            "collapsedChildren": false,
            "components": [
                {
                    "name": "transform",
                    "specifics": "{\"pos\":{\"x\":15.83899974822998,\"y\":0.05299999937415123,\"z\":16.253999710083009},\"rot\":{\"x\":0.0,\"y\":0.0,\"z\":0.0,\"w\":1.0},\"scale\":{\"x\":7.809999942779541,\"y\":1.6340068578720093,\"z\":1.0}}"
                },
                {
                    "name": "GLTFShape",
                    "specifics": "{\"assetID\":\"87e787f9-b794-46a3-bb8f-8a8b1fdcbc7d\"}"
                }
            ]
        },
        {
            "hierarchyOrder": 0.0,
            "name": "Black Gallery Info",
            "uniqueNumber": 6,
            "parent": -1,
            "exposed": false,
            "collapsedChildren": false,
            "components": [
                {
                    "name": "transform",
                    "specifics": "{\"pos\":{\"x\":14.642000198364258,\"y\":0.0,\"z\":15.079999923706055},\"rot\":{\"x\":0.0,\"y\":0.7071068286895752,\"z\":0.0,\"w\":-0.7071068286895752},\"scale\":{\"x\":7.448999881744385,\"y\":1.684000015258789,\"z\":0.9079999923706055}}"
                },
                {
                    "name": "GLTFShape",
                    "specifics": "{\"assetID\":\"731b632b-fc46-4a7c-9f87-8a26f52064a7\"}"
                }
            ]
        }
    ]
}
